{
  "instanceCount": 50,
  "iterations": 50,
  "timestamp": "2025-07-21T06:44:47.457Z",
  "measurements": [
    {
      "instanceCount": 50,
      "memoryPerInstance": 1936.96,
      "time": 0.17145799999991596
    },
    {
      "instanceCount": 50,
      "memoryPerInstance": 1888.96,
      "time": 0.13591699999994944
    },
    {
      "instanceCount": 50,
      "memoryPerInstance": 1888.64,
      "time": 0.13166599999999562
    },
    {
      "instanceCount": 50,
      "memoryPerInstance": 1888.32,
      "time": 0.12970800000005056
    },
    {
      "instanceCount": 50,
      "memoryPerInstance": 1888.32,
      "time": 0.13066600000001927
    },
    {
      "instanceCount": 50,
      "memoryPerInstance": 1888.64,
      "time": 0.13220799999999144
    },
    {
      "instanceCount": 50,
      "memoryPerInstance": 7985.28,
      "time": 0.15912500000001728
    },
    {
      "instanceCount": 50,
      "memoryPerInstance": 1889.44,
      "time": 0.30912499999999454
    },
    {
      "instanceCount": 50,
      "memoryPerInstance": 1888.32,
      "time": 0.15658399999995254
    },
    {
      "instanceCount": 50,
      "memoryPerInstance": 1888.32,
      "time": 0.14870800000005602
    },
    {
      "instanceCount": 50,
      "memoryPerInstance": 1889.12,
      "time": 0.15583400000002712
    },
    {
      "instanceCount": 50,
      "memoryPerInstance": 1888.96,
      "time": 0.1455829999999878
    },
    {
      "instanceCount": 50,
      "memoryPerInstance": 1888.8,
      "time": 0.14495799999997416
    },
    {
      "instanceCount": 50,
      "memoryPerInstance": 1888.32,
      "time": 0.15579200000001947
    },
    {
      "instanceCount": 50,
      "memoryPerInstance": 1888.32,
      "time": 0.14733400000000074
    },
    {
      "instanceCount": 50,
      "memoryPerInstance": 1888.48,
      "time": 0.1587089999999307
    },
    {
      "instanceCount": 50,
      "memoryPerInstance": 5459.04,
      "time": 0.19562499999994998
    },
    {
      "instanceCount": 50,
      "memoryPerInstance": 2286.4,
      "time": 0.3576250000000982
    },
    {
      "instanceCount": 50,
      "memoryPerInstance": 5827.84,
      "time": 0.17629199999998946
    },
    {
      "instanceCount": 50,
      "memoryPerInstance": 1772.48,
      "time": 0.13137499999993452
    },
    {
      "instanceCount": 50,
      "memoryPerInstance": 1772.48,
      "time": 0.1372920000000022
    },
    {
      "instanceCount": 50,
      "memoryPerInstance": 1773.12,
      "time": 0.05441599999994651
    },
    {
      "instanceCount": 50,
      "memoryPerInstance": 1773.44,
      "time": 0.06775000000004638
    },
    {
      "instanceCount": 50,
      "memoryPerInstance": 1772.48,
      "time": 0.04654199999993125
    },
    {
      "instanceCount": 50,
      "memoryPerInstance": 1772.48,
      "time": 0.047041999999919426
    },
    {
      "instanceCount": 50,
      "memoryPerInstance": 1772.96,
      "time": 0.05120800000008785
    },
    {
      "instanceCount": 50,
      "memoryPerInstance": 1772.48,
      "time": 0.04616699999996854
    },
    {
      "instanceCount": 50,
      "memoryPerInstance": 1772.48,
      "time": 0.046542000000044936
    },
    {
      "instanceCount": 50,
      "memoryPerInstance": 11221.76,
      "time": 0.113083999999958
    },
    {
      "instanceCount": 50,
      "memoryPerInstance": 1772.8,
      "time": 0.04983299999992141
    },
    {
      "instanceCount": 50,
      "memoryPerInstance": 1772.48,
      "time": 0.3227919999999358
    },
    {
      "instanceCount": 50,
      "memoryPerInstance": 1773.6,
      "time": 0.05145900000002257
    },
    {
      "instanceCount": 50,
      "memoryPerInstance": 1772.48,
      "time": 0.41800000000000637
    },
    {
      "instanceCount": 50,
      "memoryPerInstance": 1772.48,
      "time": 0.05054100000006656
    },
    {
      "instanceCount": 50,
      "memoryPerInstance": 1772.48,
      "time": 0.05283299999996416
    },
    {
      "instanceCount": 50,
      "memoryPerInstance": 1772.48,
      "time": 0.046625000000062755
    },
    {
      "instanceCount": 50,
      "memoryPerInstance": 1772.48,
      "time": 0.04762500000003911
    },
    {
      "instanceCount": 50,
      "memoryPerInstance": 1773.12,
      "time": 0.05004200000007586
    },
    {
      "instanceCount": 50,
      "memoryPerInstance": 1772.48,
      "time": 0.04704100000003564
    },
    {
      "instanceCount": 50,
      "memoryPerInstance": 1772.48,
      "time": 0.047041999999919426
    },
    {
      "instanceCount": 50,
      "memoryPerInstance": 1772.8,
      "time": 0.05058299999996052
    },
    {
      "instanceCount": 50,
      "memoryPerInstance": 1772.48,
      "time": 0.04587500000002365
    },
    {
      "instanceCount": 50,
      "memoryPerInstance": 1773.12,
      "time": 0.04795899999999165
    },
    {
      "instanceCount": 50,
      "memoryPerInstance": 475.84,
      "time": 0.06420800000000781
    },
    {
      "instanceCount": 50,
      "memoryPerInstance": 200,
      "time": 0.10054200000001856
    },
    {
      "instanceCount": 50,
      "memoryPerInstance": 200,
      "time": 3.825166999999965
    },
    {
      "instanceCount": 50,
      "memoryPerInstance": 7536.96,
      "time": 0.6046670000000631
    },
    {
      "instanceCount": 50,
      "memoryPerInstance": 1773.28,
      "time": 0.16495800000006966
    },
    {
      "instanceCount": 50,
      "memoryPerInstance": 7288,
      "time": 0.5069580000000542
    },
    {
      "instanceCount": 50,
      "memoryPerInstance": 1922.24,
      "time": 0.885791999999924
    }
  ],
  "stats": {
    "instanceCount": 50,
    "iterations": 50,
    "memoryPerInstance": {
      "min": 200,
      "max": 11221.76,
      "average": 2426.5343999999996,
      "stdDev": 2036.2438267478276
    },
    "time": {
      "min": 0.04587500000002365,
      "max": 3.825166999999965,
      "average": 0.22929753999999775,
      "stdDev": 0.537516666163686
    },
    "status": "PASS",
    "measurements": [
      {
        "instanceCount": 50,
        "memoryPerInstance": 1936.96,
        "time": 0.17145799999991596
      },
      {
        "instanceCount": 50,
        "memoryPerInstance": 1888.96,
        "time": 0.13591699999994944
      },
      {
        "instanceCount": 50,
        "memoryPerInstance": 1888.64,
        "time": 0.13166599999999562
      },
      {
        "instanceCount": 50,
        "memoryPerInstance": 1888.32,
        "time": 0.12970800000005056
      },
      {
        "instanceCount": 50,
        "memoryPerInstance": 1888.32,
        "time": 0.13066600000001927
      },
      {
        "instanceCount": 50,
        "memoryPerInstance": 1888.64,
        "time": 0.13220799999999144
      },
      {
        "instanceCount": 50,
        "memoryPerInstance": 7985.28,
        "time": 0.15912500000001728
      },
      {
        "instanceCount": 50,
        "memoryPerInstance": 1889.44,
        "time": 0.30912499999999454
      },
      {
        "instanceCount": 50,
        "memoryPerInstance": 1888.32,
        "time": 0.15658399999995254
      },
      {
        "instanceCount": 50,
        "memoryPerInstance": 1888.32,
        "time": 0.14870800000005602
      },
      {
        "instanceCount": 50,
        "memoryPerInstance": 1889.12,
        "time": 0.15583400000002712
      },
      {
        "instanceCount": 50,
        "memoryPerInstance": 1888.96,
        "time": 0.1455829999999878
      },
      {
        "instanceCount": 50,
        "memoryPerInstance": 1888.8,
        "time": 0.14495799999997416
      },
      {
        "instanceCount": 50,
        "memoryPerInstance": 1888.32,
        "time": 0.15579200000001947
      },
      {
        "instanceCount": 50,
        "memoryPerInstance": 1888.32,
        "time": 0.14733400000000074
      },
      {
        "instanceCount": 50,
        "memoryPerInstance": 1888.48,
        "time": 0.1587089999999307
      },
      {
        "instanceCount": 50,
        "memoryPerInstance": 5459.04,
        "time": 0.19562499999994998
      },
      {
        "instanceCount": 50,
        "memoryPerInstance": 2286.4,
        "time": 0.3576250000000982
      },
      {
        "instanceCount": 50,
        "memoryPerInstance": 5827.84,
        "time": 0.17629199999998946
      },
      {
        "instanceCount": 50,
        "memoryPerInstance": 1772.48,
        "time": 0.13137499999993452
      },
      {
        "instanceCount": 50,
        "memoryPerInstance": 1772.48,
        "time": 0.1372920000000022
      },
      {
        "instanceCount": 50,
        "memoryPerInstance": 1773.12,
        "time": 0.05441599999994651
      },
      {
        "instanceCount": 50,
        "memoryPerInstance": 1773.44,
        "time": 0.06775000000004638
      },
      {
        "instanceCount": 50,
        "memoryPerInstance": 1772.48,
        "time": 0.04654199999993125
      },
      {
        "instanceCount": 50,
        "memoryPerInstance": 1772.48,
        "time": 0.047041999999919426
      },
      {
        "instanceCount": 50,
        "memoryPerInstance": 1772.96,
        "time": 0.05120800000008785
      },
      {
        "instanceCount": 50,
        "memoryPerInstance": 1772.48,
        "time": 0.04616699999996854
      },
      {
        "instanceCount": 50,
        "memoryPerInstance": 1772.48,
        "time": 0.046542000000044936
      },
      {
        "instanceCount": 50,
        "memoryPerInstance": 11221.76,
        "time": 0.113083999999958
      },
      {
        "instanceCount": 50,
        "memoryPerInstance": 1772.8,
        "time": 0.04983299999992141
      },
      {
        "instanceCount": 50,
        "memoryPerInstance": 1772.48,
        "time": 0.3227919999999358
      },
      {
        "instanceCount": 50,
        "memoryPerInstance": 1773.6,
        "time": 0.05145900000002257
      },
      {
        "instanceCount": 50,
        "memoryPerInstance": 1772.48,
        "time": 0.41800000000000637
      },
      {
        "instanceCount": 50,
        "memoryPerInstance": 1772.48,
        "time": 0.05054100000006656
      },
      {
        "instanceCount": 50,
        "memoryPerInstance": 1772.48,
        "time": 0.05283299999996416
      },
      {
        "instanceCount": 50,
        "memoryPerInstance": 1772.48,
        "time": 0.046625000000062755
      },
      {
        "instanceCount": 50,
        "memoryPerInstance": 1772.48,
        "time": 0.04762500000003911
      },
      {
        "instanceCount": 50,
        "memoryPerInstance": 1773.12,
        "time": 0.05004200000007586
      },
      {
        "instanceCount": 50,
        "memoryPerInstance": 1772.48,
        "time": 0.04704100000003564
      },
      {
        "instanceCount": 50,
        "memoryPerInstance": 1772.48,
        "time": 0.047041999999919426
      },
      {
        "instanceCount": 50,
        "memoryPerInstance": 1772.8,
        "time": 0.05058299999996052
      },
      {
        "instanceCount": 50,
        "memoryPerInstance": 1772.48,
        "time": 0.04587500000002365
      },
      {
        "instanceCount": 50,
        "memoryPerInstance": 1773.12,
        "time": 0.04795899999999165
      },
      {
        "instanceCount": 50,
        "memoryPerInstance": 475.84,
        "time": 0.06420800000000781
      },
      {
        "instanceCount": 50,
        "memoryPerInstance": 200,
        "time": 0.10054200000001856
      },
      {
        "instanceCount": 50,
        "memoryPerInstance": 200,
        "time": 3.825166999999965
      },
      {
        "instanceCount": 50,
        "memoryPerInstance": 7536.96,
        "time": 0.6046670000000631
      },
      {
        "instanceCount": 50,
        "memoryPerInstance": 1773.28,
        "time": 0.16495800000006966
      },
      {
        "instanceCount": 50,
        "memoryPerInstance": 7288,
        "time": 0.5069580000000542
      },
      {
        "instanceCount": 50,
        "memoryPerInstance": 1922.24,
        "time": 0.885791999999924
      }
    ]
  }
}